{
    "asset": {
        "format": "jpg",
        "id": "13df3e0375fcad7c451a654514957ddf",
        "name": "S005_0_7453.jpg",
        "path": "file:/home/mike/Workspace/fasteners/outputs/5class_fasteners_dataset/S005_0_7453.jpg",
        "size": {
            "width": 4032,
            "height": 1960
        },
        "state": 2,
        "type": 1
    },
    "regions": [
        {
            "id": "R-jucWUX7",
            "type": "RECTANGLE",
            "tags": [
                "S005"
            ],
            "boundingBox": {
                "height": 211.5909090909091,
                "width": 495.30434782608694,
                "left": 1780.8695652173913,
                "top": 933.1924715909091
            },
            "points": [
                {
                    "x": 1780.8695652173913,
                    "y": 933.1924715909091
                },
                {
                    "x": 2276.173913043478,
                    "y": 933.1924715909091
                },
                {
                    "x": 2276.173913043478,
                    "y": 1144.7833806818182
                },
                {
                    "x": 1780.8695652173913,
                    "y": 1144.7833806818182
                }
            ]
        }
    ],
    "version": "2.1.0"
}