{
    "asset": {
        "format": "jpg",
        "id": "1656465c163b56d1fb9262f5b9e14cbe",
        "name": "S003_0_7866.jpg",
        "path": "file:/home/mike/Workspace/fasteners/outputs/5class_fasteners_dataset/S003_0_7866.jpg",
        "size": {
            "width": 4032,
            "height": 1960
        },
        "state": 2,
        "type": 1
    },
    "regions": [
        {
            "id": "B5SxPpaYp",
            "type": "RECTANGLE",
            "tags": [
                "S003"
            ],
            "boundingBox": {
                "height": 150.3409090909091,
                "width": 289.39130434782606,
                "left": 1611.1304347826087,
                "top": 922.0561079545453
            },
            "points": [
                {
                    "x": 1611.1304347826087,
                    "y": 922.0561079545453
                },
                {
                    "x": 1900.5217391304348,
                    "y": 922.0561079545453
                },
                {
                    "x": 1900.5217391304348,
                    "y": 1072.3970170454545
                },
                {
                    "x": 1611.1304347826087,
                    "y": 1072.3970170454545
                }
            ]
        }
    ],
    "version": "2.1.0"
}