{
    "asset": {
        "format": "jpg",
        "id": "23440e14052befbcdacd1bf07cc1031c",
        "name": "S001_0_1867.jpg",
        "path": "file:/home/mike/Workspace/fasteners/outputs/5class_fasteners_dataset/S001_0_1867.jpg",
        "size": {
            "width": 4032,
            "height": 1960
        },
        "state": 2,
        "type": 1
    },
    "regions": [
        {
            "id": "sA0Sgtj9i",
            "type": "RECTANGLE",
            "tags": [
                "S001"
            ],
            "boundingBox": {
                "height": 270.0568181818182,
                "width": 865.391304347826,
                "left": 1588.8695652173913,
                "top": 924.8401988636364
            },
            "points": [
                {
                    "x": 1588.8695652173913,
                    "y": 924.8401988636364
                },
                {
                    "x": 2454.2608695652175,
                    "y": 924.8401988636364
                },
                {
                    "x": 2454.2608695652175,
                    "y": 1194.8970170454545
                },
                {
                    "x": 1588.8695652173913,
                    "y": 1194.8970170454545
                }
            ]
        }
    ],
    "version": "2.1.0"
}