<annotation verified="yes">
    <folder>Annotation</folder>
    <filename>2019-10-30-143753.mp4#t=8.666667.jpg</filename>
    <path>settings-PascalVOC-export/Annotations/2019-10-30-143753.mp4#t=8.666667.jpg</path>
    <source>
        <database>Unknown</database>
    </source>
    <size>
        <width>1184</width>
        <height>656</height>
        <depth>3</depth>
    </size>
    <segmented>0</segmented>
    <object>
    <name>S001</name>
    <pose>Unspecified</pose>
    <truncated>0</truncated>
    <difficult>0</difficult>
    <bndbox>
        <xmin>499.18866253321517</xmin>
        <ymin>203.051517571885</ymin>
        <xmax>713.1266607617359</xmax>
        <ymax>423.1154153354633</ymax>
    </bndbox>
</object>
</annotation>
