{
    "asset": {
        "format": "jpg",
        "id": "849f4a5b0765fad825dd3244f7a20d2c",
        "name": "fastener_0_3416.jpg",
        "path": "file:/home/mike/Workspace/DA/fastener/output/fastener_0_3416.jpg",
        "size": {
            "width": 4032,
            "height": 1960
        },
        "state": 2,
        "type": 1
    },
    "regions": [
        {
            "id": "R-U42xSGr",
            "type": "RECTANGLE",
            "tags": [
                "fastener"
            ],
            "boundingBox": {
                "height": 790.1424501424501,
                "width": 912.4318339100346,
                "left": 1554.2034602076126,
                "top": 503.17485754985756
            },
            "points": [
                {
                    "x": 1554.2034602076126,
                    "y": 503.17485754985756
                },
                {
                    "x": 2466.6352941176474,
                    "y": 503.17485754985756
                },
                {
                    "x": 2466.6352941176474,
                    "y": 1293.3173076923076
                },
                {
                    "x": 1554.2034602076126,
                    "y": 1293.3173076923076
                }
            ]
        }
    ],
    "version": "2.1.0"
}