<annotation>
    <folder>fasteners</folder>
    <filename>2019-11-05-153237.mp4#t=22.5-009.jpg</filename>
    <path>/home/mike/Workspace/fasteners/2019-11-05-153237.mp4#t=22.5-009.jpg</path>
    <source>
        <database>Unknown</database>
    </source>
    <size>
        <width>1600</width>
        <height>896</height>
        <depth>3</depth>
    </size>
    <segmented>0</segmented>
    <object>
        <name>S002</name>
        <pose>Unspecified</pose>
        <truncated>0</truncated>
        <difficult>0</difficult>
        <bndbox>
            <xmin>816.5388469911347</xmin>
            <ymin>0.0</ymin>
            <xmax>1403.210351339339</xmax>
            <ymax>396.39401491347326</ymax>
        </bndbox>
    </object>
</annotation>
