<annotation>
    <folder>fasteners</folder>
    <filename>2019-11-11-155510.mp4#t=2-004.jpg</filename>
    <path>/home/mike/Workspace/fasteners/2019-11-11-155510.mp4#t=2-004.jpg</path>
    <source>
        <database>Unknown</database>
    </source>
    <size>
        <width>1600</width>
        <height>896</height>
        <depth>3</depth>
    </size>
    <segmented>0</segmented>
    <object>
        <name>S001</name>
        <pose>Unspecified</pose>
        <truncated>0</truncated>
        <difficult>0</difficult>
        <bndbox>
            <xmin>300.23637956131824</xmin>
            <ymin>518.1521299023836</ymin>
            <xmax>657.9410043660655</xmax>
            <ymax>707.3655870293486</ymax>
        </bndbox>
    </object>    <object>
        <name>S002</name>
        <pose>Unspecified</pose>
        <truncated>0</truncated>
        <difficult>0</difficult>
        <bndbox>
            <xmin>406.754433816704</xmin>
            <ymin>366.1326015884032</ymin>
            <xmax>806.2856547374897</xmax>
            <ymax>787.212038512803</ymax>
        </bndbox>
    </object>
</annotation>
