<annotation>
    <folder>fasteners</folder>
    <filename>2019-11-11-155510.mp4#t=25.5-003.jpg</filename>
    <path>/home/mike/Workspace/fasteners/2019-11-11-155510.mp4#t=25.5-003.jpg</path>
    <source>
        <database>Unknown</database>
    </source>
    <size>
        <width>1600</width>
        <height>896</height>
        <depth>3</depth>
    </size>
    <segmented>0</segmented>
    <object>
        <name>S001</name>
        <pose>Unspecified</pose>
        <truncated>0</truncated>
        <difficult>0</difficult>
        <bndbox>
            <xmin>571.8992919921875</xmin>
            <ymin>369.5580749511719</ymin>
            <xmax>877.4388427734375</xmax>
            <ymax>491.0132751464844</ymax>
        </bndbox>
    </object>    <object>
        <name>S002</name>
        <pose>Unspecified</pose>
        <truncated>0</truncated>
        <difficult>0</difficult>
        <bndbox>
            <xmin>743.521484375</xmin>
            <ymin>226.66958618164062</ymin>
            <xmax>954.1487426757812</xmax>
            <ymax>621.041748046875</ymax>
        </bndbox>
    </object>
</annotation>
