<annotation>
    <folder>fasteners</folder>
    <filename>2019-10-30-143753.mp4#t=10-003.jpg</filename>
    <path>/home/mike/Workspace/fasteners/2019-10-30-143753.mp4#t=10-003.jpg</path>
    <source>
        <database>Unknown</database>
    </source>
    <size>
        <width>1184</width>
        <height>656</height>
        <depth>3</depth>
    </size>
    <segmented>0</segmented>
    <object>
        <name>S001</name>
        <pose>Unspecified</pose>
        <truncated>0</truncated>
        <difficult>0</difficult>
        <bndbox>
            <xmin>572.6488434898724</xmin>
            <ymin>263.76435648349025</ymin>
            <xmax>799.9364962570154</xmax>
            <ymax>582.7785459404885</ymax>
        </bndbox>
    </object>
</annotation>
