<annotation>
    <folder>fasteners</folder>
    <filename>2019-11-05-153237.mp4#t=17-002.jpg</filename>
    <path>/home/mike/Workspace/fasteners/2019-11-05-153237.mp4#t=17-002.jpg</path>
    <source>
        <database>Unknown</database>
    </source>
    <size>
        <width>1600</width>
        <height>896</height>
        <depth>3</depth>
    </size>
    <segmented>0</segmented>
    <object>
        <name>S002</name>
        <pose>Unspecified</pose>
        <truncated>0</truncated>
        <difficult>0</difficult>
        <bndbox>
            <xmin>865.8507004147648</xmin>
            <ymin>281.1571395372466</ymin>
            <xmax>1206.1254482618615</xmax>
            <ymax>587.4664756999396</ymax>
        </bndbox>
    </object>
</annotation>
