<annotation>
    <folder>fasteners</folder>
    <filename>2019-11-05-153237.mp4#t=28.5-009.jpg</filename>
    <path>/home/mike/Workspace/fasteners/2019-11-05-153237.mp4#t=28.5-009.jpg</path>
    <source>
        <database>Unknown</database>
    </source>
    <size>
        <width>1600</width>
        <height>896</height>
        <depth>3</depth>
    </size>
    <segmented>0</segmented>
    <object>
        <name>S002</name>
        <pose>Unspecified</pose>
        <truncated>0</truncated>
        <difficult>0</difficult>
        <bndbox>
            <xmin>323.6567044403356</xmin>
            <ymin>308.20861061751344</ymin>
            <xmax>815.9437938604985</xmax>
            <ymax>477.70130351164096</ymax>
        </bndbox>
    </object>
</annotation>
