<annotation>
    <folder>fasteners</folder>
    <filename>2019-11-11-155510.mp4#t=30-005.jpg</filename>
    <path>/home/mike/Workspace/fasteners/2019-11-11-155510.mp4#t=30-005.jpg</path>
    <source>
        <database>Unknown</database>
    </source>
    <size>
        <width>1600</width>
        <height>896</height>
        <depth>3</depth>
    </size>
    <segmented>0</segmented>
    <object>
        <name>S001</name>
        <pose>Unspecified</pose>
        <truncated>0</truncated>
        <difficult>0</difficult>
        <bndbox>
            <xmin>783.3784790039062</xmin>
            <ymin>207.9390106201172</ymin>
            <xmax>1050.627197265625</xmax>
            <ymax>391.0320739746094</ymax>
        </bndbox>
    </object>    <object>
        <name>S002</name>
        <pose>Unspecified</pose>
        <truncated>0</truncated>
        <difficult>0</difficult>
        <bndbox>
            <xmin>840.7390747070312</xmin>
            <ymin>322.5368347167969</ymin>
            <xmax>1199.243408203125</xmax>
            <ymax>516.1676025390625</ymax>
        </bndbox>
    </object>
</annotation>
