<annotation>
    <folder>fasteners</folder>
    <filename>2019-11-11-155510.mp4#t=12.5-002.jpg</filename>
    <path>/home/mike/Workspace/fasteners/2019-11-11-155510.mp4#t=12.5-002.jpg</path>
    <source>
        <database>Unknown</database>
    </source>
    <size>
        <width>1600</width>
        <height>896</height>
        <depth>3</depth>
    </size>
    <segmented>0</segmented>
    <object>
        <name>S001</name>
        <pose>Unspecified</pose>
        <truncated>0</truncated>
        <difficult>0</difficult>
        <bndbox>
            <xmin>868.1528930664062</xmin>
            <ymin>378.436767578125</ymin>
            <xmax>993.9805908203125</xmax>
            <ymax>657.0869140625</ymax>
        </bndbox>
    </object>    <object>
        <name>S002</name>
        <pose>Unspecified</pose>
        <truncated>0</truncated>
        <difficult>0</difficult>
        <bndbox>
            <xmin>711.1925048828125</xmin>
            <ymin>238.45755004882812</ymin>
            <xmax>965.4423828125</xmax>
            <ymax>558.9706420898438</ymax>
        </bndbox>
    </object>
</annotation>
