<annotation>
    <folder>fasteners</folder>
    <filename>2019-10-30-143753.mp4#t=4-001.jpg</filename>
    <path>/home/mike/Workspace/fasteners/2019-10-30-143753.mp4#t=4-001.jpg</path>
    <source>
        <database>Unknown</database>
    </source>
    <size>
        <width>1184</width>
        <height>656</height>
        <depth>3</depth>
    </size>
    <segmented>0</segmented>
    <object>
        <name>S001</name>
        <pose>Unspecified</pose>
        <truncated>0</truncated>
        <difficult>0</difficult>
        <bndbox>
            <xmin>490.3568420410156</xmin>
            <ymin>277.65838623046875</ymin>
            <xmax>742.8432006835938</xmax>
            <ymax>434.87066650390625</ymax>
        </bndbox>
    </object>
</annotation>
