<annotation>
    <folder>fasteners</folder>
    <filename>2019-11-05-153237.mp4#t=41-009.jpg</filename>
    <path>/home/mike/Workspace/fasteners/2019-11-05-153237.mp4#t=41-009.jpg</path>
    <source>
        <database>Unknown</database>
    </source>
    <size>
        <width>1600</width>
        <height>896</height>
        <depth>3</depth>
    </size>
    <segmented>0</segmented>
    <object>
        <name>S002</name>
        <pose>Unspecified</pose>
        <truncated>0</truncated>
        <difficult>0</difficult>
        <bndbox>
            <xmin>732.4987792968749</xmin>
            <ymin>326.86761474609375</ymin>
            <xmax>1070.34521484375</xmax>
            <ymax>565.2776184082031</ymax>
        </bndbox>
    </object>
</annotation>
